[
    {
        "id": "0335-000",
        "time": "03:35",
        "quote_time_case": "3:35",
        "quote_first": "Três e meia, ",
        "quote_last": ", 3:40. De repente, houve um forte solavanco que quase o jogou para fora da cadeira. Foi seguido por um barulho alto de rodas enquanto o trem desacelerava rapidamente e finalmente parava.",
        "title": "Cuidado com o que você deseja",
        "author": "Jeffrey Archer",
        "sfw": "sfw"
    },
    {
        "id": "0335-001",
        "time": "03:35",
        "quote_time_case": "3h35",
        "quote_first": "Ele só conseguia ver os ponteiros do despertador na escuridão: ",
        "quote_last": " Ajustou o travesseiro e fechou os olhos.",
        "title": "Os cães de Riga",
        "author": "Henning Mankell",
        "sfw": "unknown"
    }
]