[
    {
        "id": "001877",
        "time": "12:10",
        "quote_time_case": "doze-dez",
        "quote_first": "A criança disse que eram ",
        "quote_last": " e que Gonda já estava atrasado. Outra criança disse que talvez a chuva o tenha atrasado. Outro disse: não, não é chuva, seu diretor estava pegando um avião de Hollywood.",
        "title": "Enoque e o Gorila",
        "author": "Flannery O'Connor",
        "sfw": "unknown"
    },
    {
        "id": "001878",
        "time": "12:10",
        "quote_time_case": "meio-dia e dez",
        "quote_first": "Escondi minha cesta de trapos sujos e cera de tartaruga perto da porta de saída do fliperama. Eram ",
        "quote_last": ", mas naquele momento não era por comida que eu estava com fome. Caminhei lentamente ao longo da pista e entrei na Horror House.",
        "title": "Joyland",
        "author": "Stephen King",
        "sfw": "unknown"
    },
    {
        "id": "001879",
        "time": "12:10",
        "quote_time_case": "meio-dia, e dez minutos depois",
        "quote_first": "Madame Dumas chegou ao ",
        "quote_last": " Trause entregou-lhe seu cartão do caixa eletrônico e instruiu-a a ir ao Citibank do bairro perto de Sheridan Square e transferir quarenta mil dólares de suas economias conta para sua conta corrente.",
        "title": "Noite do Oráculo",
        "author": "Paul Auster",
        "sfw": "unknown"
    },
    {
        "id": "001880",
        "time": "12:10",
        "quote_time_case": "doze-dez",
        "quote_first": "Pagaram apenas um quarto e mantiveram Einstein com eles porque não precisariam de privacidade para fazer amor. Exausto, Travis mal conseguiu beijar Nora antes de cair em um sono profundo. Ele sonhava com coisas com olhos amarelos, cabeças disformes e bocas de crocodilo cheias de dentes de tubarão. Ele acordou cinco horas depois, às ",
        "quote_last": " quinta-feira à tarde.",
        "title": "Observadores",
        "author": "Dean Koontz",
        "sfw": "unknown"
    }
]