[
    {
        "id": "000337",
        "time": "02:27",
        "quote_time_case": "2:27",
        "quote_first": "La demande a été accordée, mais seulement après qu'un autre formulaire ait été rempli et signé. Dexter Hutchins a passé un appel à frais virés au directeur de la CIA à ",
        "quote_last": " ce matin-là.",
        "title": "Honneur parmi les voleurs",
        "author": "Jeffrey Archer",
        "sfw": "sfw"
    },
    {
        "id": "000338",
        "time": "02:27",
        "quote_time_case": "deux heures vingt-sept minutes",
        "quote_first": "Les aiguilles des quatre mille horloges électriques des quatre mille pièces du Bloomsbury Centre indiquaient ",
        "quote_last": ".",
        "title": "Meilleur des Mondes",
        "author": "Aldous Leonard Huxley",
        "sfw": "unknown"
    },
    {
        "id": "000339",
        "time": "02:27",
        "quote_time_case": "2h27",
        "quote_first": "La lune n’a brillé à nouveau que ",
        "quote_last": ". C'était suffisant pour montrer à Wallander qu'il se trouvait à une certaine distance en dessous de l'arbre.",
        "title": "Un pas en arrière",
        "author": "Henning Mankell",
        "sfw": "unknown"
    }
]