[
    {
        "id": "003499",
        "time": "23:25",
        "quote_time_case": "23h25",
        "quote_first": "OK Estelle, je serai à l'aéroport de Nice à ",
        "quote_last": ". samedi, BA : Pourriez-vous envoyer le chauffeur ?",
        "title": "L'argent des autres",
        "author": "Justin Cartwright",
        "sfw": "unknown"
    },
    {
        "id": "003500",
        "time": "23:25",
        "quote_time_case": "* onze heures et vingt-cinq minutes",
        "quote_first": "Pour tester l'intensité de la lumière dont il ne parvenait pas à déterminer la nature et la cause, il sortit sa montre pour voir s'il distinguait les chiffres sur le cadran. Ils étaient bien visibles et les aiguilles indiquaient onze heures vingt-cinq minutes. À ce moment-là, la mystérieuse illumination s’éclaira soudain d’une splendeur intense, presque aveuglante…",
        "quote_last": "",
        "title": "Un message sans fil",
        "author": "Ambrose Bierce",
        "sfw": "unknown"
    }
]