[
    {
        "time": "10:16",
        "quote_first": "",
        "quote_last": " Enfin. Quarante minutes de travail acharné et j'ai fait précisément un lit. Je suis loin derrière. Mais tant pis. Continuez simplement à bouger. Laverie ensuite.",
        "quote_time_case": "10h16",
        "quote_raw": "10h16 Enfin. Quarante minutes de travail acharné et j'ai fait précisément un lit. Je suis loin derrière. Mais tant pis. Continuez simplement à bouger. Laverie ensuite.",
        "title": "La déesse non domestique",
        "author": "Sophie Kinsella",
        "sfw": "unknown"
    }
]