[
    {
        "time": "11:31",
        "quote_first": "Albatross 8 pasó sobre Pamlico Sound a las 11:31 hora local. Su programación a bordo fue diseñada para rastrear receptores térmicos en todo el horizonte visible, interrogando todo lo que está a la vista y fijando cualquier firma que se ajuste a sus parámetros de adquisición.",
        "quote_last": "",
        "quote_time_case": "* 1131",
        "title": "La caza del Octubre Rojo",
        "author": "Tom Clancy",
        "sfw": "unknown"
    }
]