[
    {
        "time": "20:10",
        "quote_first": "Son las ",
        "quote_last": ". Debo decirte cuánto te amo a las ocho y diez de la tarde de un domingo 27 de enero de 1918.",
        "quote_time_case": "ocho y diez minutos",
        "title": "Carta a John Middleton Murry",
        "author": "Katherine Mansfield",
        "sfw": "unknown"
    },
    {
        "time": "20:10",
        "quote_first": "8:10 P.M.<br>Incluso en una noche normal, La Verdad era intolerable. El suelo estaba cubierto de aserrín, música que solo podía describirse como metal metálico sonaba en el sistema de sonido, las luces navideñas parpadeaban fuera de sincronización a un ritmo que provocaba dolor de cabeza y las paredes estaban cubiertas con carteles de madera falsos y hogareños que decían mierda. como:<br>NUNCA ERES<br>2 VIEJO<br>2 BEBIDA<br>2 MUCHOS<br>6 PAQUETES",
        "quote_last": "",
        "quote_time_case": "* 8:10 p.m.",
        "title": "Cocinas del Gran Medio Oeste",
        "author": "J. Ryan Stradal",
        "sfw": "nsfw"
    },
    {
        "time": "20:10",
        "quote_first": "A las 20.10 h. El 1 de abril Y.D.A.U., el agregado médico todavía está observando el cartucho de entretenimiento sin etiqueta.",
        "quote_last": "",
        "quote_time_case": "* 2010 h.",
        "title": "Frivolidad infinita",
        "author": "David Foster Wallace",
        "sfw": "unknown"
    }
]