[
    {
        "time": "21:04",
        "quote_first": "A la luz de una linterna de haz estrecho, Pierce consultó su reloj. Eran las ",
        "quote_last": ". Eso les dio una hora para encontrar la llave antes de que Barlow les proporcionara su distracción para cubrir su fuga.",
        "quote_time_case": "9:04",
        "title": "El gran robo del tren",
        "author": "Michael Crichton",
        "sfw": "sfw"
    },
    {
        "time": "21:04",
        "quote_first": "9:04 p.m.<br>\"¿Qué te parece una ETA de 02:00 horas?\" Dimitri Spiros estaba utilizando una radio no asegurada, pero no tenía otra opción. \"Eso nos dará unas veintinueve horas. Tiempo suficiente para tener todo junto\".",
        "quote_last": "",
        "quote_time_case": "* 21:04",
        "title": "Proyecto cíclope",
        "author": "Thomas Hoover",
        "sfw": "sfw"
    },
    {
        "time": "21:04",
        "quote_first": "A las 21.04 horas, los trilobites nadan en escena, seguidos más o menos inmediatamente por las bien formadas criaturas de Burgess Shale.",
        "quote_last": "",
        "quote_time_case": "* 21:04",
        "title": "Una breve historia de casi todo",
        "author": "Bill Bryson",
        "sfw": "sfw"
    }
]