[
    {
        "id": "0111-000",
        "time": "01:11",
        "quote_time_case": "più vicina all’una e mezza",
        "quote_first": "Dichiara che uno dei camerieri era in preda all’alcol e che gli stava dando una medicazione. Inoltre era ",
        "quote_last": ".",
        "title": "La relazione al ballo della vittoria",
        "author": "Agatha Christie",
        "sfw": "unknown"
    },
    {
        "id": "0111-001",
        "time": "01:11",
        "quote_time_case": "l’una e undici minuti",
        "quote_first": "Ho lasciato la porta socchiusa e all’",
        "quote_last": " ho sentito Harvey attraversare il soggiorno. Si udì un gorgoglio mentre beveva un sorso da una delle bottiglie sul carrello. Uscì dalla porta principale il più silenziosamente possibile. Lo osservavo dalla finestra; era solo.",
        "title": "Cervello da miliardi di dollari",
        "author": "Len Deighton",
        "sfw": "sfw"
    }
]