[
    {
        "id": "000629",
        "time": "04:47",
        "quote_time_case": "4:47",
        "quote_first": "Ho dormito solo a intermittenza dopo aver cercato online. Le frasi che avevo letto si ripetevano nella mia testa ancora e ancora. Quando mi sono svegliato per quella che mi è sembrata la centesima volta, l'orologio dello Stormtrooper accanto al letto diceva <-<-<-<",
        "quote_last": ">->->->.",
        "title": "Quello che sapeva",
        "author": "Gilly MacMillan",
        "sfw": "unknown"
    }
]