[
    {
        "time": "11:44",
        "quote_first": "L'orologio di Weiss segnava le dodici meno sedici e la detonazione era fissata per mezzogiorno, secondo quanto impostato da una serie di orologi elettrici e tre cavi di controllo separati. Ma quando il drago abbracciò la bomba e rafforzò la presa, ciò fu sufficiente.",
        "quote_last": "",
        "quote_time_case": "dodici minuti meno sedici",
        "quote_raw": "L'orologio di Weiss segnava le dodici meno sedici e la detonazione era fissata per mezzogiorno, secondo quanto impostato da una serie di orologi elettrici e tre cavi di controllo separati. Ma quando il drago abbracciò la bomba e rafforzò la presa, ciò fu sufficiente.",
        "title": "Per tenere il ponte",
        "author": "Garth Nix",
        "sfw": "sfw"
    }
]