[
    {
        "time": "20:53",
        "quote_first": "Apenas oito e cinquenta e três. A reunião de decisão dos sócios começa em sete minutos. Não tenho certeza se posso suportar isso.",
        "quote_last": "",
        "quote_time_case": "* oito cinquenta e três",
        "quote_raw": "Apenas oito e cinquenta e três. A reunião de decisão dos sócios começa em sete minutos. Não tenho certeza se posso suportar isso.",
        "title": "A Deusa Não Doméstica",
        "author": "Sophie Kinsella",
        "sfw": "unknown"
    }
]