[
    {
        "id": "0315-000",
        "time": "03:15",
        "quote_time_case": "tres-quince",
        "quote_first": "El jefe había tenido algo mucho más espectacular que una evacuación intestinal; a las ",
        "quote_last": " ese día había hecho algo en sus pantalones que era el equivalente a una bomba atómica de mierda.",
        "title": "Los Tommyknockers",
        "author": "Stephen King",
        "sfw": "nsfw"
    },
    {
        "id": "0315-001",
        "time": "03:15",
        "quote_time_case": "las tres y cuarto de la mañana",
        "quote_first": "Una noche de agosto, una vez terminada la buena recolección y la tripulación de Old Pie pagando y regresando a la reserva, me desperté con el mugido de una vaca. <em>Me quedé dormido a la hora de ordeñar</em>, pensé, pero cuando saqué el reloj de bolsillo de mi padre de la mesa al lado de mi cama y lo miré, vi que era ",
        "quote_last": ".",
        "title": "Completamente oscuro, sin estrellas",
        "author": "Stephen King",
        "sfw": "unknown"
    },
    {
        "id": "0315-002",
        "time": "03:15",
        "quote_time_case": "3:15",
        "quote_first": "Sobre la puerta de la habitación 69 el reloj marcaba las ",
        "quote_last": ". El movimiento se estaba acelerando. Lo que una vez había sido el gimnasio era ahora una pequeña habitación, de dos metros de ancho, un cubo estrecho, casi perfecto.",
        "title": "Pozo 69",
        "author": "J.G. Ballard",
        "sfw": "unknown"
    }
]