[
    {
        "id": "000790",
        "time": "05:59",
        "quote_time_case": "seis menos un minuto",
        "quote_first": "A las ",
        "quote_last": ", Hollis sacó su reloj. Suspiró, volvió a colocar el reloj y se reclinó en su silla. Una mirada por la ventana le mostró que la calle estaba desierta excepto por aquí y allá un poni de vaca inclinado sobre uno de los rieles de enganche y uno o dos carros parados frente a una tienda.",
        "title": "La llegada de la ley",
        "author": "Charles Alden Seltzer",
        "sfw": "sfw"
    },
    {
        "id": "000791",
        "time": "05:59",
        "quote_time_case": "antes de que el reloj diera las seis",
        "quote_first": "Las persianas de la habitación de la esquina sureste fueron las primeras en levantarse. Era el dormitorio del viejo rector. Estaba leyendo su Biblia ",
        "quote_last": ".",
        "title": "El martillo de Dios",
        "author": "Bo Giertz",
        "sfw": "unknown"
    },
    {
        "id": "000792",
        "time": "05:59",
        "quote_time_case": "La del alba",
        "quote_first": "",
        "quote_last": " sería cuando don Quijote salió de la venta, tan contento, tan gallardo, tan alborozado por verse ya armado caballero, que el gozo le reventaba por las cinchas del caballo.",
        "title": "Don Quijote de la Mancha",
        "author": "Miguel de Cervantes",
        "sfw": "sfw"
    }
]