[
    {
        "id": "001022",
        "time": "07:49",
        "quote_time_case": "Ocho menos once",
        "quote_first": "",
        "quote_last": ".<br>“Siempre tienes razón; debe haber un reloj en tu cabeza.”",
        "title": "El fin del principio",
        "author": "Ray Bradbury",
        "sfw": "unknown"
    },
    {
        "id": "001023",
        "time": "07:49",
        "quote_time_case": "ocho menos once",
        "quote_first": "¿Cuándo volvió a ver al Dr. Wellesley?<br>“Sólo ",
        "quote_last": ".”<br>“¿Dónde?”<br>“En la consulta. “<br>“¿Regresó allí?”<br>“Sí”.<br>“¿Cómo se fija esa hora precisa: las ocho menos once?”<br>“Porque había quedado con un paciente En Meadow Gate, a las ocho menos diez, miré el reloj cuando entró, vi qué hora era y le recordé la cita.",
        "title": "En el salón del alcalde",
        "author": "J.S. Fletcher",
        "sfw": "unknown"
    }
]