[
    {
        "id": "001795",
        "time": "11:50",
        "quote_time_case": "diez minutos antes del mediodía",
        "quote_first": "A las 11:38, dejó su escritorio y caminó hacia la puerta lateral del auditorio, llegando ",
        "quote_last": ".",
        "title": "El círculo",
        "author": "Dave Eggers",
        "sfw": "unknown"
    },
    {
        "id": "001796",
        "time": "11:50",
        "quote_time_case": "las doce menos diez",
        "quote_first": "El hombre que se los entregó le entregó un billete de diez chelines y le prometió otro si se lo entregaba exactamente ",
        "quote_last": ".",
        "title": "La aventura de Johnnie Waverley: una historia de Hércules Poirot",
        "author": "Agatha Christie",
        "sfw": "unknown"
    }
]