[
    {
        "id": "1520-000",
        "time": "15:20",
        "quote_time_case": "3:20",
        "quote_first": "James se tapó las orejas con el trilby, miró hacia otro lado y pasó el tiempo charlando con Sam O’Flaherty sobre el ",
        "quote_last": ", el rey Jorge VI y la reina Isabel. Apuestas.",
        "title": "Ni un centavo más, ni un centavo menos",
        "author": "Jeffrey Archer",
        "sfw": "sfw"
    },
    {
        "id": "1520-001",
        "time": "15:20",
        "quote_time_case": "3:20",
        "quote_first": "Miró su reloj. Sólo ",
        "quote_last": ", pero eso estaba lo suficientemente cerca para el trabajo del gobierno. Claudette Albertson lo sorprendió. “No, es el Sr. Hayes, aquí abajo, en el primer piso, con nosotros”.<br>“¿Estás seguro?” Dan había jugado una partida de damas con Charlie Hayes esa misma tarde y, para ser un hombre con leucemia mielógena aguda, parecía tan animado como un grillo.",
        "title": "Doctor Dormir",
        "author": "Stephen King",
        "sfw": "unknown"
    },
    {
        "id": "1520-002",
        "time": "15:20",
        "quote_time_case": "tres y veinte",
        "quote_first": "Cuando el teléfono sonó a las ",
        "quote_last": " estaba tirado en el tatami, comenzando por el techo. Un charco de luz solar invernal se había formado en el lugar donde yacía. Como una mosca muerta, yací allí, vacío, bajo un foco de diciembre de 1971.",
        "title": "Sauce ciego, mujer dormida",
        "author": "Haruki Murakami",
        "sfw": "unknown"
    },
    {
        "id": "1520-003",
        "time": "15:20",
        "quote_time_case": "las tres y veinte minutos",
        "quote_first": "A ",
        "quote_last": " del lunes 26 de enero de 1948, en Tokio, y estoy bebiendo y estoy bebiendo y estoy bebiendo y estoy bebiendo y estoy bebiendo y Estoy bebiendo y estoy bebiendo y estoy bebiendo y estoy bebiendo.",
        "title": "Ciudad ocupada",
        "author": "David Peace",
        "sfw": "unknown"
    }
]