[
    {
        "id": "1804-000",
        "time": "18:04",
        "quote_time_case": "Cuatro minutos después de las seis",
        "quote_first": "Lo dejaremos constancia, mi Rosannah; cada año, al sonar esta querida hora en el reloj, la celebraremos con acciones de gracias, todos los años de nuestra vida.<br>“¡Lo haremos, lo haremos, Alonzo!”<br>“",
        "quote_last": ", de la tarde, mi Rosannah…”",
        "title": "Los amores de Alonzo Fitz Clarence y Rosannah Ethelton",
        "author": "Mark Twain",
        "sfw": "unknown"
    }
]