[
    {
        "id": "003471",
        "time": "22:56",
        "quote_time_case": "22.56 horas",
        "quote_first": "El reloj marcaba las ",
        "quote_last": ". Eso significaba que había estado fuera durante veinte minutos. Dormir veinte minutos. Sólo una buena siesta. En ese tiempo había engañado a una mafia y perdido ocho mil dólares.",
        "title": "Adiós mi amor",
        "author": "Raymond Chandler",
        "sfw": "sfw"
    },
    {
        "id": "003472",
        "time": "22:56",
        "quote_time_case": "alrededor de las once",
        "quote_first": "Eran ",
        "quote_last": ". Las estrellas brillaban. El viento soplaba suavemente y traía de los campos el olor a hojas podridas y a nieve derretida.",
        "title": "El martillo de Dios",
        "author": "Bo Giertz",
        "sfw": "unknown"
    }
]