[
    {
        "id": "002521",
        "time": "16:45",
        "quote_time_case": "* seize heures quarante-cinq",
        "quote_first": "\"Quand avez-vous dit que vous retourniez à Amsterdam ?\"<br>\"Vous savez exactement quand, car je vous l'ai dit : demain matin.\"<br>\"Pouvez-vous revenir plus tôt ?\"<br>\"Je pourrais. Il y a un vol KLM à 16h45. aujourd’hui, cela me permettrait d’arriver à Amsterdam juste avant six heures.",
        "quote_last": "",
        "title": "Les Sans-Nom",
        "author": "John Connolly",
        "sfw": "unknown"
    },
    {
        "id": "002522",
        "time": "16:45",
        "quote_time_case": "* quatrecent-quarante-cinq",
        "quote_first": "A quatre heures quarante-cinq, Miss Haddon alla prendre le thé avec le directeur, qui lui expliqua pourquoi elle désirait que tous les élèves apprennent le même duo. Cela faisait partie de son nouveau système de coordination.",
        "quote_last": "",
        "title": "Coordination",
        "author": "E.M. Forster",
        "sfw": "unknown"
    },
    {
        "id": "002523",
        "time": "16:45",
        "quote_time_case": "cinq heures moins quinze",
        "quote_first": "Le lendemain, Bill ne prit que dix minutes sur les vingt minutes de pause prévues pour l'après-midi et partit à ",
        "quote_last": ". Il gara la voiture dans le parking au moment où Arlene descendait du bus.",
        "title": "D'où j'appelle",
        "author": "Raymond Carver",
        "sfw": "unknown"
    }
]